tsmtool/__init__.py
tsmtool/__main__.py
tsmtool/cli.py
tsmtool/tarsnap.py
tsmtool/version.py
tsmtool-1.2.7.dist-info/entry_points.txt
tsmtool-1.2.7.dist-info/LICENSE
tsmtool-1.2.7.dist-info/WHEEL
tsmtool-1.2.7.dist-info/METADATA
tsmtool-1.2.7.dist-info/RECORD
