Metadata-Version: 2.3
Name: tsmtool
Version: 1.2.7
Summary: Top-level package for tsmtool.
Keywords: tsmtool
Author-email: Matt Krueger <mkrueger@rstms.net>
Classifier: Intended Audience :: Developers
Classifier: Natural Language :: English
Classifier: Programming Language :: Python :: 3
Classifier: Programming Language :: Python :: 3.8
Classifier: Programming Language :: Python :: 3.9
Classifier: Programming Language :: Python :: 3.10
Requires-Dist: bs4
Requires-Dist: click
Requires-Dist: requests
Requires-Dist: tabulate
Requires-Dist: black ; extra == "dev"
Requires-Dist: bump2version ; extra == "dev"
Requires-Dist: coverage ; extra == "dev"
Requires-Dist: flake8 ; extra == "dev"
Requires-Dist: flit ; extra == "dev"
Requires-Dist: pytest ; extra == "dev"
Requires-Dist: pytest-datadir ; extra == "dev"
Requires-Dist: tox ; extra == "dev"
Requires-Dist: pdbpp ; extra == "dev"
Requires-Dist: m2r2 ; extra == "docs"
Requires-Dist: Sphinx ; extra == "docs"
Requires-Dist: sphinx-click ; extra == "docs"
Requires-Dist: sphinx-rtd-theme ; extra == "docs"
Project-URL: Home, https://github.com/rstms/tsmtool
Provides-Extra: dev
Provides-Extra: docs
